managpu/__init__.py
managpu/_choice/__init__.py
managpu/_choice/_gpu_manager.py
managpu/_choice/_gpu_utils.py
managpu/pytorch_tool/__init__.py
managpu/pytorch_tool/_pt_tool.py
managpu/tensorflow_tool/__init__.py
managpu/tensorflow_tool/_tf_tool.py
managpu-1.2.4.dist-info/LICENSE
managpu-1.2.4.dist-info/METADATA
managpu-1.2.4.dist-info/WHEEL
managpu-1.2.4.dist-info/top_level.txt
managpu-1.2.4.dist-info/RECORD
